{
  "studio-open-web": {},
  "Saitek PLC Saitek P2600 Rumble Force Pad": {
    "jogKinz": "rz",
    "jogLink": "x",
    "jogKinslider": "slider",
    "jogKiny": "y",
    "jogKinx": "x"
  },
  "studio-open-git": {
    "https://gist.github.com/2db3bc51e779a9fd0a6e99226f018e20.git:minkowsky.groovy": [
      "https://gist.github.com/2db3bc51e779a9fd0a6e99226f018e20.git",
      "minkowsky.groovy"
    ],
    "https://gist.github.com/1599152e4f4797f53e816bf169057427.git:terrain.groovy": [
      "https://gist.github.com/1599152e4f4797f53e816bf169057427.git",
      "terrain.groovy"
    ],
    "https://gist.github.com/f4b5d8b74f1c69a5c53e913fe36d88b8.git:ExtrudeBezierAPI.groovy": [
      "https://gist.github.com/f4b5d8b74f1c69a5c53e913fe36d88b8.git",
      "ExtrudeBezierAPI.groovy"
    ]
  },
  "BowlerStudioConfigs": {
    "firstVersion": "0.20.7",
    "skinBranch": "0.20.8",
    "skinRepo": "https://github.com/madhephaestus/BowlerStudioImageAssets.git",
    "notifiedArduinoDep": true
  }
}